rapidpredict/__init__.py
rapidpredict/supervised.py
rapidpredict-0.0.0.9.dist-info/METADATA
rapidpredict-0.0.0.9.dist-info/WHEEL
rapidpredict-0.0.0.9.dist-info/top_level.txt
rapidpredict-0.0.0.9.dist-info/RECORD
