Metadata-Version: 2.1
Name: rapidpredict
Version: 0.0.0.9
Summary: rapid predict is a python package to simplifies the process of fitting and evaluating multiple machine learning models on a dataset.
Author: Synthetic Dataset AI Team
Author-email: <nematiusa@gmail.com>
Keywords: python,pandas,numpy,scikit-learn,scipy,matplotlib,seaborn
Classifier: Development Status :: 1 - Planning
Classifier: Intended Audience :: Developers
Classifier: Programming Language :: Python :: 3
Classifier: Operating System :: Unix
Classifier: Operating System :: MacOS :: MacOS X
Classifier: Operating System :: Microsoft :: Windows
Classifier: License :: Free To Use But Restricted
Requires-Python: >=3.7
Requires-Dist: click
Requires-Dist: scikit-learn
Requires-Dist: pandas
Requires-Dist: tqdm
Requires-Dist: joblib
Requires-Dist: lightgbm
Requires-Dist: xgboost
Requires-Dist: itables
Requires-Dist: catboost
Requires-Dist: colorlover
Requires-Dist: seaborn
Requires-Dist: plotly
Requires-Dist: IPython
